py_currency_converter/__init__.py
py_currency_converter/py_exchange_rate.py
py_custom_spellrectify/__init__.py
py_custom_spellrectify/rectifier.py
py_custom_spellrectify-1.0.0.dist-info/LICENSE
py_custom_spellrectify-1.0.0.dist-info/METADATA
py_custom_spellrectify-1.0.0.dist-info/WHEEL
py_custom_spellrectify-1.0.0.dist-info/top_level.txt
py_custom_spellrectify-1.0.0.dist-info/RECORD
