Metadata-Version: 2.1
Name: py-custom-spellrectify
Version: 1.0.0
Summary: Python Custom Spell Rectifier
Home-page: https://github.com/vimal-dharmalingam/py_custom_spellrectify
Author: Vimal Dharmalingam
Author-email: vimald8959@gmail.com
License: UNKNOWN
Platform: UNKNOWN
Classifier: Programming Language :: Python :: 3
Classifier: License :: OSI Approved :: MIT License
Classifier: Operating System :: OS Independent
Requires-Dist: requests (>=1.16.4)
